{
  "easy": [
    "World War I",
    "World War II",
    "American Civil War",
    "Vietnam War",
    "American Revolution",
    "French Revolution",
    "Gulf War",
    "Korean War",
    "Napoleonic Wars",
    "Cold War",
    "Persian Gulf War",
    "War of 1812",
    "Desert Storm",
    "Operation Iraqi Freedom",
    "US Civil War",
    "WW1",
    "WW2",
    "Battle of Gettysburg",
    "The Revolutionary War",
    "The Hundred Years' War",
    "The Crimean War",
    "The Falklands War",
    "The French and Indian War",
    "The Iraq War",
    "The War of 1812",
    "The Boer War",
    "The Korean Conflict",
    "The Gulf Conflict",
    "The Vietnam Conflict",
    "The American Indian Wars"
  ],
  "easy-medium": [
    "Peloponnesian War",
    "Hundred Years' War",
    "Opium Wars",
    "Franco-Prussian War",
    "Russo-Japanese War",
    "Punic Wars",
    "Afghanistan War",
    "Congo Wars",
    "Sino-Indian War",
    "Winter War"
  ],
  "medium": [
    "Opium War",
    "Seven Years War",
    "Falklands War"
  ],
  "medium-hard": [
    "War of the Oaken Bucket",
    "Aroostook War",
    "Carnatic Wars",
    "Kashmir War",
    "Mughal-Maratha Wars"
  ],
  "hard": [
    "War of the Oaken Wands",
    "Kampot War",
    "War of Chōshō",
    "Strzelecki War",
    "War of the Grandson"
  ]
}